[
    {
        "title": "Ommomme Heego",
        "filmAlbum": "Hudugaata",
        "year": "2007",
        "musicDirector": "",
        "composer": "Jassie Gift",
        "lyricist": "Kaviraj",
        "cosinger": "Alisha Chinai",
        "language": "Kannada",
        "url": "https://www.youtube.com/watch?v=TzVLyKN1sZA"
    },
    {
        "title": "Holihadu",
        "filmAlbum": "Parichaya",
        "year": "2009",
        "musicDirector": "",
        "composer": "Jassie Gift",
        "lyricist": "Jayanth Kaikini",
        "cosinger": "H.G. Chaitra, Jassie Gift",
        "language": "Kannada",
        "url": "https://www.youtube.com/watch?v=9bdRqBvYIqo"
    },
    {
        "title": "Amma Neene Thane",
        "filmAlbum": "Maha Roudram",
        "year": "2022",
        "musicDirector": "",
        "composer": "Aditya Aashish Singh",
        "lyricist": "",
        "cosinger": "Aaditya Aashish Singh",
        "language": "Kannada",
        "url": "https://www.youtube.com/watch?v=npptBvvAi1M"
    }
]